logging_actions/__init__.py
logging_actions/py.typed
logging_actions-0.1.7.dist-info/WHEEL
logging_actions-0.1.7.dist-info/METADATA
logging_actions-0.1.7.dist-info/RECORD
