Metadata-Version: 2.1
Name: logging-actions
Version: 0.1.7
Summary: For easy configuration of `logging.Logger`s with `argparse.Action`s.
Home-page: https://github.com/aatifsyed/logging-actions
Author: Aatif Syed
Author-email: aatifsyedyp@gmail.com
Requires-Python: >=3.6.2,<4.0.0
Classifier: Programming Language :: Python :: 3
Classifier: Programming Language :: Python :: 3.10
Classifier: Programming Language :: Python :: 3.7
Classifier: Programming Language :: Python :: 3.8
Classifier: Programming Language :: Python :: 3.9
Project-URL: Repository, https://github.com/aatifsyed/logging-actions
